{
  "users_statistic": [
    { "user_id": 1, "date": "2019-10-15", "page_views": 967, "clicks": 947 },
    { "user_id": 2, "date": "2019-10-15", "page_views": 932, "clicks": 452 },
    { "user_id": 4, "date": "2019-10-15", "page_views": 231, "clicks": 302 },
    { "user_id": 5, "date": "2019-10-15", "page_views": 126, "clicks": 456 },
    { "user_id": 7, "date": "2019-10-15", "page_views": 487, "clicks": 430 },
    { "user_id": 8, "date": "2019-10-15", "page_views": 734, "clicks": 196 },
    { "user_id": 10, "date": "2019-10-15", "page_views": 938, "clicks": 887 },
    { "user_id": 13, "date": "2019-10-15", "page_views": 911, "clicks": 131 },
    { "user_id": 15, "date": "2019-10-15", "page_views": 716, "clicks": 588 },
    { "user_id": 18, "date": "2019-10-15", "page_views": 963, "clicks": 145 },
    { "user_id": 21, "date": "2019-10-15", "page_views": 383, "clicks": 241 },
    { "user_id": 22, "date": "2019-10-15", "page_views": 833, "clicks": 392 },
    { "user_id": 23, "date": "2019-10-15", "page_views": 341, "clicks": 870 },
    { "user_id": 26, "date": "2019-10-15", "page_views": 138, "clicks": 456 },
    { "user_id": 27, "date": "2019-10-15", "page_views": 252, "clicks": 996 },
    { "user_id": 29, "date": "2019-10-15", "page_views": 367, "clicks": 533 },
    { "user_id": 32, "date": "2019-10-15", "page_views": 605, "clicks": 591 },
    { "user_id": 33, "date": "2019-10-15", "page_views": 428, "clicks": 235 },
    { "user_id": 34, "date": "2019-10-15", "page_views": 460, "clicks": 589 },
    { "user_id": 35, "date": "2019-10-15", "page_views": 123, "clicks": 623 },
    { "user_id": 37, "date": "2019-10-15", "page_views": 452, "clicks": 295 },
    { "user_id": 38, "date": "2019-10-15", "page_views": 238, "clicks": 575 },
    { "user_id": 39, "date": "2019-10-15", "page_views": 710, "clicks": 782 },
    { "user_id": 40, "date": "2019-10-15", "page_views": 388, "clicks": 159 },
    { "user_id": 41, "date": "2019-10-15", "page_views": 936, "clicks": 234 },
    { "user_id": 42, "date": "2019-10-15", "page_views": 401, "clicks": 314 },
    { "user_id": 43, "date": "2019-10-15", "page_views": 974, "clicks": 313 },
    { "user_id": 44, "date": "2019-10-15", "page_views": 815, "clicks": 625 },
    { "user_id": 45, "date": "2019-10-15", "page_views": 518, "clicks": 562 },
    { "user_id": 46, "date": "2019-10-15", "page_views": 840, "clicks": 746 },
    { "user_id": 48, "date": "2019-10-15", "page_views": 659, "clicks": 330 },
    { "user_id": 49, "date": "2019-10-15", "page_views": 881, "clicks": 127 },
    { "user_id": 50, "date": "2019-10-15", "page_views": 354, "clicks": 149 },
    { "user_id": 53, "date": "2019-10-15", "page_views": 102, "clicks": 497 },
    { "user_id": 55, "date": "2019-10-15", "page_views": 191, "clicks": 429 },
    { "user_id": 56, "date": "2019-10-15", "page_views": 260, "clicks": 357 },
    { "user_id": 57, "date": "2019-10-15", "page_views": 297, "clicks": 146 },
    { "user_id": 58, "date": "2019-10-15", "page_views": 793, "clicks": 138 },
    { "user_id": 59, "date": "2019-10-15", "page_views": 738, "clicks": 151 },
    { "user_id": 60, "date": "2019-10-15", "page_views": 446, "clicks": 564 },
    { "user_id": 63, "date": "2019-10-15", "page_views": 251, "clicks": 597 },
    { "user_id": 64, "date": "2019-10-15", "page_views": 326, "clicks": 253 },
    { "user_id": 65, "date": "2019-10-15", "page_views": 475, "clicks": 931 },
    { "user_id": 67, "date": "2019-10-15", "page_views": 154, "clicks": 111 },
    { "user_id": 69, "date": "2019-10-15", "page_views": 463, "clicks": 124 },
    { "user_id": 71, "date": "2019-10-15", "page_views": 233, "clicks": 711 },
    { "user_id": 73, "date": "2019-10-15", "page_views": 436, "clicks": 542 },
    { "user_id": 74, "date": "2019-10-15", "page_views": 476, "clicks": 967 },
    { "user_id": 75, "date": "2019-10-15", "page_views": 778, "clicks": 392 },
    { "user_id": 77, "date": "2019-10-15", "page_views": 298, "clicks": 873 },
    { "user_id": 78, "date": "2019-10-15", "page_views": 871, "clicks": 226 },
    { "user_id": 79, "date": "2019-10-15", "page_views": 743, "clicks": 287 },
    { "user_id": 80, "date": "2019-10-15", "page_views": 200, "clicks": 236 },
    { "user_id": 81, "date": "2019-10-15", "page_views": 249, "clicks": 586 },
    { "user_id": 82, "date": "2019-10-15", "page_views": 420, "clicks": 722 },
    { "user_id": 84, "date": "2019-10-15", "page_views": 185, "clicks": 845 },
    { "user_id": 85, "date": "2019-10-15", "page_views": 185, "clicks": 598 },
    { "user_id": 86, "date": "2019-10-15", "page_views": 282, "clicks": 144 },
    { "user_id": 87, "date": "2019-10-15", "page_views": 601, "clicks": 151 },
    { "user_id": 89, "date": "2019-10-15", "page_views": 230, "clicks": 652 },
    { "user_id": 90, "date": "2019-10-15", "page_views": 182, "clicks": 448 },
    { "user_id": 92, "date": "2019-10-15", "page_views": 950, "clicks": 883 },
    { "user_id": 93, "date": "2019-10-15", "page_views": 666, "clicks": 123 },
    { "user_id": 94, "date": "2019-10-15", "page_views": 417, "clicks": 940 },
    { "user_id": 95, "date": "2019-10-15", "page_views": 603, "clicks": 210 },
    { "user_id": 96, "date": "2019-10-15", "page_views": 411, "clicks": 365 },
    { "user_id": 99, "date": "2019-10-15", "page_views": 540, "clicks": 109 },
    { "user_id": 100, "date": "2019-10-15", "page_views": 159, "clicks": 905 },
    { "user_id": 101, "date": "2019-10-15", "page_views": 821, "clicks": 358 },
    { "user_id": 104, "date": "2019-10-15", "page_views": 912, "clicks": 220 },
    { "user_id": 106, "date": "2019-10-15", "page_views": 682, "clicks": 149 },
    { "user_id": 107, "date": "2019-10-15", "page_views": 834, "clicks": 301 },
    { "user_id": 109, "date": "2019-10-15", "page_views": 474, "clicks": 597 },
    { "user_id": 110, "date": "2019-10-15", "page_views": 352, "clicks": 192 },
    { "user_id": 111, "date": "2019-10-15", "page_views": 546, "clicks": 285 },
    { "user_id": 112, "date": "2019-10-15", "page_views": 189, "clicks": 917 },
    { "user_id": 113, "date": "2019-10-15", "page_views": 917, "clicks": 506 },
    { "user_id": 114, "date": "2019-10-15", "page_views": 305, "clicks": 684 },
    { "user_id": 115, "date": "2019-10-15", "page_views": 450, "clicks": 784 },
    { "user_id": 116, "date": "2019-10-15", "page_views": 360, "clicks": 528 },
    { "user_id": 119, "date": "2019-10-15", "page_views": 192, "clicks": 801 },
    { "user_id": 121, "date": "2019-10-15", "page_views": 551, "clicks": 968 },
    { "user_id": 123, "date": "2019-10-15", "page_views": 190, "clicks": 117 },
    { "user_id": 126, "date": "2019-10-15", "page_views": 548, "clicks": 914 },
    { "user_id": 128, "date": "2019-10-15", "page_views": 846, "clicks": 730 },
    { "user_id": 130, "date": "2019-10-15", "page_views": 589, "clicks": 622 },
    { "user_id": 132, "date": "2019-10-15", "page_views": 678, "clicks": 622 },
    { "user_id": 133, "date": "2019-10-15", "page_views": 898, "clicks": 497 },
    { "user_id": 134, "date": "2019-10-15", "page_views": 748, "clicks": 204 },
    { "user_id": 135, "date": "2019-10-15", "page_views": 218, "clicks": 924 },
    { "user_id": 136, "date": "2019-10-15", "page_views": 864, "clicks": 356 },
    { "user_id": 138, "date": "2019-10-15", "page_views": 739, "clicks": 538 },
    { "user_id": 139, "date": "2019-10-15", "page_views": 743, "clicks": 968 },
    { "user_id": 141, "date": "2019-10-15", "page_views": 870, "clicks": 142 },
    { "user_id": 142, "date": "2019-10-15", "page_views": 406, "clicks": 561 },
    { "user_id": 144, "date": "2019-10-15", "page_views": 583, "clicks": 514 },
    { "user_id": 146, "date": "2019-10-15", "page_views": 466, "clicks": 365 },
    { "user_id": 147, "date": "2019-10-15", "page_views": 314, "clicks": 812 },
    { "user_id": 149, "date": "2019-10-15", "page_views": 821, "clicks": 675 },
    { "user_id": 150, "date": "2019-10-15", "page_views": 701, "clicks": 565 },
    { "user_id": 1, "date": "2019-10-16", "page_views": 616, "clicks": 597 },
    { "user_id": 2, "date": "2019-10-16", "page_views": 547, "clicks": 660 },
    { "user_id": 3, "date": "2019-10-16", "page_views": 699, "clicks": 289 },
    { "user_id": 4, "date": "2019-10-16", "page_views": 466, "clicks": 123 },
    { "user_id": 5, "date": "2019-10-16", "page_views": 163, "clicks": 550 },
    { "user_id": 6, "date": "2019-10-16", "page_views": 718, "clicks": 223 },
    { "user_id": 7, "date": "2019-10-16", "page_views": 144, "clicks": 791 },
    { "user_id": 8, "date": "2019-10-16", "page_views": 181, "clicks": 327 },
    { "user_id": 9, "date": "2019-10-16", "page_views": 167, "clicks": 613 },
    { "user_id": 10, "date": "2019-10-16", "page_views": 885, "clicks": 959 },
    { "user_id": 13, "date": "2019-10-16", "page_views": 648, "clicks": 199 },
    { "user_id": 15, "date": "2019-10-16", "page_views": 779, "clicks": 533 },
    { "user_id": 18, "date": "2019-10-16", "page_views": 763, "clicks": 804 },
    { "user_id": 21, "date": "2019-10-16", "page_views": 378, "clicks": 694 },
    { "user_id": 22, "date": "2019-10-16", "page_views": 790, "clicks": 666 },
    { "user_id": 23, "date": "2019-10-16", "page_views": 586, "clicks": 424 },
    { "user_id": 25, "date": "2019-10-16", "page_views": 627, "clicks": 993 },
    { "user_id": 26, "date": "2019-10-16", "page_views": 486, "clicks": 114 },
    { "user_id": 27, "date": "2019-10-16", "page_views": 664, "clicks": 957 },
    { "user_id": 29, "date": "2019-10-16", "page_views": 269, "clicks": 520 },
    { "user_id": 30, "date": "2019-10-16", "page_views": 152, "clicks": 463 },
    { "user_id": 32, "date": "2019-10-16", "page_views": 551, "clicks": 272 },
    { "user_id": 33, "date": "2019-10-16", "page_views": 965, "clicks": 915 },
    { "user_id": 34, "date": "2019-10-16", "page_views": 211, "clicks": 187 },
    { "user_id": 35, "date": "2019-10-16", "page_views": 165, "clicks": 255 },
    { "user_id": 37, "date": "2019-10-16", "page_views": 713, "clicks": 409 },
    { "user_id": 38, "date": "2019-10-16", "page_views": 126, "clicks": 491 },
    { "user_id": 39, "date": "2019-10-16", "page_views": 656, "clicks": 874 },
    { "user_id": 40, "date": "2019-10-16", "page_views": 983, "clicks": 666 },
    { "user_id": 41, "date": "2019-10-16", "page_views": 511, "clicks": 676 },
    { "user_id": 42, "date": "2019-10-16", "page_views": 633, "clicks": 796 },
    { "user_id": 43, "date": "2019-10-16", "page_views": 194, "clicks": 100 },
    { "user_id": 44, "date": "2019-10-16", "page_views": 213, "clicks": 473 },
    { "user_id": 45, "date": "2019-10-16", "page_views": 943, "clicks": 249 },
    { "user_id": 46, "date": "2019-10-16", "page_views": 898, "clicks": 888 },
    { "user_id": 47, "date": "2019-10-16", "page_views": 646, "clicks": 539 },
    { "user_id": 48, "date": "2019-10-16", "page_views": 220, "clicks": 237 },
    { "user_id": 49, "date": "2019-10-16", "page_views": 134, "clicks": 734 },
    { "user_id": 50, "date": "2019-10-16", "page_views": 872, "clicks": 193 },
    { "user_id": 53, "date": "2019-10-16", "page_views": 507, "clicks": 372 },
    { "user_id": 55, "date": "2019-10-16", "page_views": 560, "clicks": 501 },
    { "user_id": 56, "date": "2019-10-16", "page_views": 718, "clicks": 569 },
    { "user_id": 57, "date": "2019-10-16", "page_views": 380, "clicks": 504 },
    { "user_id": 58, "date": "2019-10-16", "page_views": 299, "clicks": 177 },
    { "user_id": 59, "date": "2019-10-16", "page_views": 915, "clicks": 707 },
    { "user_id": 60, "date": "2019-10-16", "page_views": 825, "clicks": 559 },
    { "user_id": 63, "date": "2019-10-16", "page_views": 755, "clicks": 397 },
    { "user_id": 64, "date": "2019-10-16", "page_views": 598, "clicks": 904 },
    { "user_id": 65, "date": "2019-10-16", "page_views": 426, "clicks": 149 },
    { "user_id": 66, "date": "2019-10-16", "page_views": 350, "clicks": 700 },
    { "user_id": 67, "date": "2019-10-16", "page_views": 299, "clicks": 209 },
    { "user_id": 68, "date": "2019-10-16", "page_views": 758, "clicks": 803 },
    { "user_id": 69, "date": "2019-10-16", "page_views": 218, "clicks": 957 },
    { "user_id": 71, "date": "2019-10-16", "page_views": 838, "clicks": 192 },
    { "user_id": 73, "date": "2019-10-16", "page_views": 137, "clicks": 226 },
    { "user_id": 74, "date": "2019-10-16", "page_views": 635, "clicks": 291 },
    { "user_id": 75, "date": "2019-10-16", "page_views": 859, "clicks": 581 },
    { "user_id": 77, "date": "2019-10-16", "page_views": 689, "clicks": 803 },
    { "user_id": 78, "date": "2019-10-16", "page_views": 542, "clicks": 837 },
    { "user_id": 79, "date": "2019-10-16", "page_views": 856, "clicks": 952 },
    { "user_id": 80, "date": "2019-10-16", "page_views": 898, "clicks": 905 },
    { "user_id": 81, "date": "2019-10-16", "page_views": 828, "clicks": 107 },
    { "user_id": 82, "date": "2019-10-16", "page_views": 917, "clicks": 306 },
    { "user_id": 84, "date": "2019-10-16", "page_views": 330, "clicks": 580 },
    { "user_id": 85, "date": "2019-10-16", "page_views": 550, "clicks": 669 },
    { "user_id": 86, "date": "2019-10-16", "page_views": 224, "clicks": 763 },
    { "user_id": 87, "date": "2019-10-16", "page_views": 876, "clicks": 609 },
    { "user_id": 89, "date": "2019-10-16", "page_views": 121, "clicks": 742 },
    { "user_id": 90, "date": "2019-10-16", "page_views": 640, "clicks": 249 },
    { "user_id": 92, "date": "2019-10-16", "page_views": 445, "clicks": 490 },
    { "user_id": 93, "date": "2019-10-16", "page_views": 966, "clicks": 176 },
    { "user_id": 94, "date": "2019-10-16", "page_views": 951, "clicks": 426 },
    { "user_id": 95, "date": "2019-10-16", "page_views": 945, "clicks": 272 },
    { "user_id": 96, "date": "2019-10-16", "page_views": 114, "clicks": 421 },
    { "user_id": 99, "date": "2019-10-16", "page_views": 640, "clicks": 743 },
    { "user_id": 100, "date": "2019-10-16", "page_views": 491, "clicks": 590 },
    { "user_id": 101, "date": "2019-10-16", "page_views": 473, "clicks": 114 },
    { "user_id": 103, "date": "2019-10-16", "page_views": 374, "clicks": 858 },
    { "user_id": 104, "date": "2019-10-16", "page_views": 445, "clicks": 133 },
    { "user_id": 106, "date": "2019-10-16", "page_views": 199, "clicks": 101 },
    { "user_id": 107, "date": "2019-10-16", "page_views": 341, "clicks": 844 },
    { "user_id": 109, "date": "2019-10-16", "page_views": 132, "clicks": 169 },
    { "user_id": 110, "date": "2019-10-16", "page_views": 859, "clicks": 150 },
    { "user_id": 111, "date": "2019-10-16", "page_views": 847, "clicks": 690 },
    { "user_id": 112, "date": "2019-10-16", "page_views": 792, "clicks": 272 },
    { "user_id": 113, "date": "2019-10-16", "page_views": 317, "clicks": 498 },
    { "user_id": 114, "date": "2019-10-16", "page_views": 882, "clicks": 275 },
    { "user_id": 115, "date": "2019-10-16", "page_views": 705, "clicks": 306 },
    { "user_id": 116, "date": "2019-10-16", "page_views": 946, "clicks": 844 },
    { "user_id": 117, "date": "2019-10-16", "page_views": 733, "clicks": 267 },
    { "user_id": 119, "date": "2019-10-16", "page_views": 483, "clicks": 446 },
    { "user_id": 121, "date": "2019-10-16", "page_views": 822, "clicks": 269 },
    { "user_id": 123, "date": "2019-10-16", "page_views": 397, "clicks": 806 },
    { "user_id": 124, "date": "2019-10-16", "page_views": 168, "clicks": 819 },
    { "user_id": 126, "date": "2019-10-16", "page_views": 286, "clicks": 436 },
    { "user_id": 128, "date": "2019-10-16", "page_views": 128, "clicks": 316 },
    { "user_id": 130, "date": "2019-10-16", "page_views": 212, "clicks": 426 },
    { "user_id": 132, "date": "2019-10-16", "page_views": 691, "clicks": 698 },
    { "user_id": 133, "date": "2019-10-16", "page_views": 273, "clicks": 385 },
    { "user_id": 134, "date": "2019-10-16", "page_views": 439, "clicks": 437 },
    { "user_id": 135, "date": "2019-10-16", "page_views": 246, "clicks": 817 },
    { "user_id": 136, "date": "2019-10-16", "page_views": 189, "clicks": 450 },
    { "user_id": 138, "date": "2019-10-16", "page_views": 929, "clicks": 423 },
    { "user_id": 139, "date": "2019-10-16", "page_views": 193, "clicks": 747 },
    { "user_id": 141, "date": "2019-10-16", "page_views": 585, "clicks": 448 },
    { "user_id": 142, "date": "2019-10-16", "page_views": 359, "clicks": 496 },
    { "user_id": 143, "date": "2019-10-16", "page_views": 403, "clicks": 960 },
    { "user_id": 144, "date": "2019-10-16", "page_views": 772, "clicks": 750 },
    { "user_id": 146, "date": "2019-10-16", "page_views": 266, "clicks": 582 },
    { "user_id": 147, "date": "2019-10-16", "page_views": 778, "clicks": 504 },
    { "user_id": 149, "date": "2019-10-16", "page_views": 483, "clicks": 733 },
    { "user_id": 150, "date": "2019-10-16", "page_views": 145, "clicks": 990 },
    { "user_id": 1, "date": "2019-10-17", "page_views": 218, "clicks": 291 },
    { "user_id": 2, "date": "2019-10-17", "page_views": 753, "clicks": 454 },
    { "user_id": 3, "date": "2019-10-17", "page_views": 769, "clicks": 127 },
    { "user_id": 4, "date": "2019-10-17", "page_views": 150, "clicks": 300 },
    { "user_id": 5, "date": "2019-10-17", "page_views": 874, "clicks": 354 },
    { "user_id": 6, "date": "2019-10-17", "page_views": 788, "clicks": 814 },
    { "user_id": 7, "date": "2019-10-17", "page_views": 723, "clicks": 170 },
    { "user_id": 8, "date": "2019-10-17", "page_views": 514, "clicks": 206 },
    { "user_id": 9, "date": "2019-10-17", "page_views": 523, "clicks": 358 },
    { "user_id": 10, "date": "2019-10-17", "page_views": 368, "clicks": 548 },
    { "user_id": 11, "date": "2019-10-17", "page_views": 190, "clicks": 840 },
    { "user_id": 12, "date": "2019-10-17", "page_views": 951, "clicks": 131 },
    { "user_id": 13, "date": "2019-10-17", "page_views": 543, "clicks": 446 },
    { "user_id": 15, "date": "2019-10-17", "page_views": 764, "clicks": 740 },
    { "user_id": 18, "date": "2019-10-17", "page_views": 123, "clicks": 554 },
    { "user_id": 21, "date": "2019-10-17", "page_views": 158, "clicks": 626 },
    { "user_id": 22, "date": "2019-10-17", "page_views": 166, "clicks": 663 },
    { "user_id": 23, "date": "2019-10-17", "page_views": 257, "clicks": 368 },
    { "user_id": 25, "date": "2019-10-17", "page_views": 979, "clicks": 588 },
    { "user_id": 26, "date": "2019-10-17", "page_views": 952, "clicks": 837 },
    { "user_id": 27, "date": "2019-10-17", "page_views": 929, "clicks": 440 },
    { "user_id": 29, "date": "2019-10-17", "page_views": 773, "clicks": 263 },
    { "user_id": 30, "date": "2019-10-17", "page_views": 897, "clicks": 710 },
    { "user_id": 32, "date": "2019-10-17", "page_views": 517, "clicks": 355 },
    { "user_id": 33, "date": "2019-10-17", "page_views": 429, "clicks": 619 },
    { "user_id": 34, "date": "2019-10-17", "page_views": 513, "clicks": 107 },
    { "user_id": 35, "date": "2019-10-17", "page_views": 870, "clicks": 112 },
    { "user_id": 37, "date": "2019-10-17", "page_views": 721, "clicks": 449 },
    { "user_id": 38, "date": "2019-10-17", "page_views": 535, "clicks": 926 },
    { "user_id": 39, "date": "2019-10-17", "page_views": 167, "clicks": 829 },
    { "user_id": 40, "date": "2019-10-17", "page_views": 835, "clicks": 803 },
    { "user_id": 41, "date": "2019-10-17", "page_views": 503, "clicks": 568 },
    { "user_id": 42, "date": "2019-10-17", "page_views": 965, "clicks": 739 },
    { "user_id": 43, "date": "2019-10-17", "page_views": 424, "clicks": 838 },
    { "user_id": 44, "date": "2019-10-17", "page_views": 326, "clicks": 441 },
    { "user_id": 45, "date": "2019-10-17", "page_views": 631, "clicks": 231 },
    { "user_id": 46, "date": "2019-10-17", "page_views": 446, "clicks": 932 },
    { "user_id": 47, "date": "2019-10-17", "page_views": 487, "clicks": 708 },
    { "user_id": 48, "date": "2019-10-17", "page_views": 557, "clicks": 592 },
    { "user_id": 49, "date": "2019-10-17", "page_views": 783, "clicks": 927 },
    { "user_id": 50, "date": "2019-10-17", "page_views": 427, "clicks": 877 },
    { "user_id": 52, "date": "2019-10-17", "page_views": 846, "clicks": 364 },
    { "user_id": 53, "date": "2019-10-17", "page_views": 746, "clicks": 345 },
    { "user_id": 54, "date": "2019-10-17", "page_views": 291, "clicks": 720 },
    { "user_id": 55, "date": "2019-10-17", "page_views": 481, "clicks": 566 },
    { "user_id": 56, "date": "2019-10-17", "page_views": 601, "clicks": 742 },
    { "user_id": 57, "date": "2019-10-17", "page_views": 180, "clicks": 806 },
    { "user_id": 58, "date": "2019-10-17", "page_views": 460, "clicks": 800 },
    { "user_id": 59, "date": "2019-10-17", "page_views": 220, "clicks": 891 },
    { "user_id": 60, "date": "2019-10-17", "page_views": 385, "clicks": 976 },
    { "user_id": 63, "date": "2019-10-17", "page_views": 955, "clicks": 532 },
    { "user_id": 64, "date": "2019-10-17", "page_views": 446, "clicks": 762 },
    { "user_id": 65, "date": "2019-10-17", "page_views": 802, "clicks": 170 },
    { "user_id": 66, "date": "2019-10-17", "page_views": 520, "clicks": 340 },
    { "user_id": 67, "date": "2019-10-17", "page_views": 884, "clicks": 545 },
    { "user_id": 68, "date": "2019-10-17", "page_views": 404, "clicks": 581 },
    { "user_id": 69, "date": "2019-10-17", "page_views": 244, "clicks": 804 },
    { "user_id": 71, "date": "2019-10-17", "page_views": 886, "clicks": 794 },
    { "user_id": 73, "date": "2019-10-17", "page_views": 594, "clicks": 584 },
    { "user_id": 74, "date": "2019-10-17", "page_views": 433, "clicks": 200 },
    { "user_id": 75, "date": "2019-10-17", "page_views": 925, "clicks": 172 },
    { "user_id": 76, "date": "2019-10-17", "page_views": 238, "clicks": 596 },
    { "user_id": 77, "date": "2019-10-17", "page_views": 146, "clicks": 415 },
    { "user_id": 78, "date": "2019-10-17", "page_views": 985, "clicks": 469 },
    { "user_id": 79, "date": "2019-10-17", "page_views": 185, "clicks": 234 },
    { "user_id": 80, "date": "2019-10-17", "page_views": 117, "clicks": 491 },
    { "user_id": 81, "date": "2019-10-17", "page_views": 449, "clicks": 306 },
    { "user_id": 82, "date": "2019-10-17", "page_views": 671, "clicks": 968 },
    { "user_id": 84, "date": "2019-10-17", "page_views": 973, "clicks": 994 },
    { "user_id": 85, "date": "2019-10-17", "page_views": 683, "clicks": 173 },
    { "user_id": 86, "date": "2019-10-17", "page_views": 993, "clicks": 148 },
    { "user_id": 87, "date": "2019-10-17", "page_views": 265, "clicks": 379 },
    { "user_id": 88, "date": "2019-10-17", "page_views": 953, "clicks": 232 },
    { "user_id": 89, "date": "2019-10-17", "page_views": 488, "clicks": 962 },
    { "user_id": 90, "date": "2019-10-17", "page_views": 468, "clicks": 289 },
    { "user_id": 92, "date": "2019-10-17", "page_views": 530, "clicks": 237 },
    { "user_id": 93, "date": "2019-10-17", "page_views": 388, "clicks": 988 },
    { "user_id": 94, "date": "2019-10-17", "page_views": 338, "clicks": 984 },
    { "user_id": 95, "date": "2019-10-17", "page_views": 207, "clicks": 533 },
    { "user_id": 96, "date": "2019-10-17", "page_views": 907, "clicks": 544 },
    { "user_id": 99, "date": "2019-10-17", "page_views": 488, "clicks": 357 },
    { "user_id": 100, "date": "2019-10-17", "page_views": 412, "clicks": 786 },
    { "user_id": 101, "date": "2019-10-17", "page_views": 249, "clicks": 314 },
    { "user_id": 103, "date": "2019-10-17", "page_views": 431, "clicks": 515 },
    { "user_id": 104, "date": "2019-10-17", "page_views": 311, "clicks": 691 },
    { "user_id": 106, "date": "2019-10-17", "page_views": 749, "clicks": 558 },
    { "user_id": 107, "date": "2019-10-17", "page_views": 122, "clicks": 741 },
    { "user_id": 109, "date": "2019-10-17", "page_views": 651, "clicks": 917 },
    { "user_id": 110, "date": "2019-10-17", "page_views": 945, "clicks": 342 },
    { "user_id": 111, "date": "2019-10-17", "page_views": 609, "clicks": 493 },
    { "user_id": 112, "date": "2019-10-17", "page_views": 306, "clicks": 609 },
    { "user_id": 113, "date": "2019-10-17", "page_views": 451, "clicks": 426 },
    { "user_id": 114, "date": "2019-10-17", "page_views": 330, "clicks": 335 },
    { "user_id": 115, "date": "2019-10-17", "page_views": 211, "clicks": 479 },
    { "user_id": 116, "date": "2019-10-17", "page_views": 519, "clicks": 557 },
    { "user_id": 117, "date": "2019-10-17", "page_views": 839, "clicks": 772 },
    { "user_id": 119, "date": "2019-10-17", "page_views": 293, "clicks": 121 },
    { "user_id": 121, "date": "2019-10-17", "page_views": 979, "clicks": 373 },
    { "user_id": 123, "date": "2019-10-17", "page_views": 508, "clicks": 201 },
    { "user_id": 124, "date": "2019-10-17", "page_views": 961, "clicks": 458 },
    { "user_id": 126, "date": "2019-10-17", "page_views": 173, "clicks": 900 },
    { "user_id": 127, "date": "2019-10-17", "page_views": 953, "clicks": 452 },
    { "user_id": 128, "date": "2019-10-17", "page_views": 922, "clicks": 467 },
    { "user_id": 130, "date": "2019-10-17", "page_views": 538, "clicks": 818 },
    { "user_id": 132, "date": "2019-10-17", "page_views": 264, "clicks": 756 },
    { "user_id": 133, "date": "2019-10-17", "page_views": 741, "clicks": 639 },
    { "user_id": 134, "date": "2019-10-17", "page_views": 233, "clicks": 654 },
    { "user_id": 135, "date": "2019-10-17", "page_views": 405, "clicks": 530 },
    { "user_id": 136, "date": "2019-10-17", "page_views": 874, "clicks": 199 },
    { "user_id": 138, "date": "2019-10-17", "page_views": 674, "clicks": 629 },
    { "user_id": 139, "date": "2019-10-17", "page_views": 213, "clicks": 548 },
    { "user_id": 141, "date": "2019-10-17", "page_views": 376, "clicks": 825 },
    { "user_id": 142, "date": "2019-10-17", "page_views": 319, "clicks": 841 },
    { "user_id": 143, "date": "2019-10-17", "page_views": 352, "clicks": 696 },
    { "user_id": 144, "date": "2019-10-17", "page_views": 526, "clicks": 674 },
    { "user_id": 146, "date": "2019-10-17", "page_views": 909, "clicks": 639 },
    { "user_id": 147, "date": "2019-10-17", "page_views": 615, "clicks": 545 },
    { "user_id": 149, "date": "2019-10-17", "page_views": 732, "clicks": 508 },
    { "user_id": 150, "date": "2019-10-17", "page_views": 542, "clicks": 293 },
    { "user_id": 1, "date": "2019-10-18", "page_views": 697, "clicks": 563 },
    { "user_id": 2, "date": "2019-10-18", "page_views": 567, "clicks": 487 },
    { "user_id": 3, "date": "2019-10-18", "page_views": 999, "clicks": 103 },
    { "user_id": 4, "date": "2019-10-18", "page_views": 106, "clicks": 351 },
    { "user_id": 5, "date": "2019-10-18", "page_views": 917, "clicks": 274 },
    { "user_id": 6, "date": "2019-10-18", "page_views": 581, "clicks": 755 },
    { "user_id": 7, "date": "2019-10-18", "page_views": 645, "clicks": 674 },
    { "user_id": 8, "date": "2019-10-18", "page_views": 751, "clicks": 201 },
    { "user_id": 9, "date": "2019-10-18", "page_views": 241, "clicks": 348 },
    { "user_id": 10, "date": "2019-10-18", "page_views": 876, "clicks": 708 },
    { "user_id": 11, "date": "2019-10-18", "page_views": 754, "clicks": 456 },
    { "user_id": 12, "date": "2019-10-18", "page_views": 714, "clicks": 352 },
    { "user_id": 13, "date": "2019-10-18", "page_views": 908, "clicks": 827 },
    { "user_id": 14, "date": "2019-10-18", "page_views": 705, "clicks": 494 },
    { "user_id": 15, "date": "2019-10-18", "page_views": 548, "clicks": 467 },
    { "user_id": 18, "date": "2019-10-18", "page_views": 810, "clicks": 784 },
    { "user_id": 21, "date": "2019-10-18", "page_views": 387, "clicks": 546 },
    { "user_id": 22, "date": "2019-10-18", "page_views": 915, "clicks": 262 },
    { "user_id": 23, "date": "2019-10-18", "page_views": 703, "clicks": 737 },
    { "user_id": 25, "date": "2019-10-18", "page_views": 248, "clicks": 954 },
    { "user_id": 26, "date": "2019-10-18", "page_views": 575, "clicks": 829 },
    { "user_id": 27, "date": "2019-10-18", "page_views": 787, "clicks": 236 },
    { "user_id": 29, "date": "2019-10-18", "page_views": 475, "clicks": 603 },
    { "user_id": 30, "date": "2019-10-18", "page_views": 323, "clicks": 287 },
    { "user_id": 32, "date": "2019-10-18", "page_views": 228, "clicks": 187 },
    { "user_id": 33, "date": "2019-10-18", "page_views": 810, "clicks": 672 },
    { "user_id": 34, "date": "2019-10-18", "page_views": 922, "clicks": 601 },
    { "user_id": 35, "date": "2019-10-18", "page_views": 726, "clicks": 634 },
    { "user_id": 37, "date": "2019-10-18", "page_views": 289, "clicks": 532 },
    { "user_id": 38, "date": "2019-10-18", "page_views": 474, "clicks": 864 },
    { "user_id": 39, "date": "2019-10-18", "page_views": 990, "clicks": 661 },
    { "user_id": 40, "date": "2019-10-18", "page_views": 555, "clicks": 254 },
    { "user_id": 41, "date": "2019-10-18", "page_views": 871, "clicks": 562 },
    { "user_id": 42, "date": "2019-10-18", "page_views": 978, "clicks": 644 },
    { "user_id": 43, "date": "2019-10-18", "page_views": 543, "clicks": 323 },
    { "user_id": 44, "date": "2019-10-18", "page_views": 311, "clicks": 439 },
    { "user_id": 45, "date": "2019-10-18", "page_views": 141, "clicks": 287 },
    { "user_id": 46, "date": "2019-10-18", "page_views": 844, "clicks": 669 },
    { "user_id": 47, "date": "2019-10-18", "page_views": 160, "clicks": 798 },
    { "user_id": 48, "date": "2019-10-18", "page_views": 265, "clicks": 999 },
    { "user_id": 49, "date": "2019-10-18", "page_views": 315, "clicks": 261 },
    { "user_id": 50, "date": "2019-10-18", "page_views": 879, "clicks": 204 },
    { "user_id": 51, "date": "2019-10-18", "page_views": 766, "clicks": 159 },
    { "user_id": 52, "date": "2019-10-18", "page_views": 713, "clicks": 353 },
    { "user_id": 53, "date": "2019-10-18", "page_views": 887, "clicks": 509 },
    { "user_id": 54, "date": "2019-10-18", "page_views": 653, "clicks": 782 },
    { "user_id": 55, "date": "2019-10-18", "page_views": 216, "clicks": 259 },
    { "user_id": 56, "date": "2019-10-18", "page_views": 457, "clicks": 516 },
    { "user_id": 57, "date": "2019-10-18", "page_views": 317, "clicks": 861 },
    { "user_id": 58, "date": "2019-10-18", "page_views": 986, "clicks": 479 },
    { "user_id": 59, "date": "2019-10-18", "page_views": 977, "clicks": 976 },
    { "user_id": 60, "date": "2019-10-18", "page_views": 549, "clicks": 147 },
    { "user_id": 63, "date": "2019-10-18", "page_views": 122, "clicks": 507 },
    { "user_id": 64, "date": "2019-10-18", "page_views": 646, "clicks": 170 },
    { "user_id": 65, "date": "2019-10-18", "page_views": 991, "clicks": 852 },
    { "user_id": 66, "date": "2019-10-18", "page_views": 900, "clicks": 236 },
    { "user_id": 67, "date": "2019-10-18", "page_views": 861, "clicks": 402 },
    { "user_id": 68, "date": "2019-10-18", "page_views": 235, "clicks": 150 },
    { "user_id": 69, "date": "2019-10-18", "page_views": 361, "clicks": 994 },
    { "user_id": 71, "date": "2019-10-18", "page_views": 278, "clicks": 451 },
    { "user_id": 73, "date": "2019-10-18", "page_views": 938, "clicks": 160 },
    { "user_id": 74, "date": "2019-10-18", "page_views": 689, "clicks": 357 },
    { "user_id": 75, "date": "2019-10-18", "page_views": 852, "clicks": 299 },
    { "user_id": 76, "date": "2019-10-18", "page_views": 891, "clicks": 315 },
    { "user_id": 77, "date": "2019-10-18", "page_views": 581, "clicks": 266 },
    { "user_id": 78, "date": "2019-10-18", "page_views": 163, "clicks": 673 },
    { "user_id": 79, "date": "2019-10-18", "page_views": 569, "clicks": 721 },
    { "user_id": 80, "date": "2019-10-18", "page_views": 887, "clicks": 355 },
    { "user_id": 81, "date": "2019-10-18", "page_views": 133, "clicks": 744 },
    { "user_id": 82, "date": "2019-10-18", "page_views": 593, "clicks": 758 },
    { "user_id": 84, "date": "2019-10-18", "page_views": 523, "clicks": 130 },
    { "user_id": 85, "date": "2019-10-18", "page_views": 963, "clicks": 144 },
    { "user_id": 86, "date": "2019-10-18", "page_views": 872, "clicks": 778 },
    { "user_id": 87, "date": "2019-10-18", "page_views": 617, "clicks": 410 },
    { "user_id": 88, "date": "2019-10-18", "page_views": 483, "clicks": 470 },
    { "user_id": 89, "date": "2019-10-18", "page_views": 271, "clicks": 295 },
    { "user_id": 90, "date": "2019-10-18", "page_views": 914, "clicks": 684 },
    { "user_id": 92, "date": "2019-10-18", "page_views": 303, "clicks": 661 },
    { "user_id": 93, "date": "2019-10-18", "page_views": 856, "clicks": 556 },
    { "user_id": 94, "date": "2019-10-18", "page_views": 263, "clicks": 618 },
    { "user_id": 95, "date": "2019-10-18", "page_views": 919, "clicks": 777 },
    { "user_id": 96, "date": "2019-10-18", "page_views": 129, "clicks": 686 },
    { "user_id": 99, "date": "2019-10-18", "page_views": 256, "clicks": 987 },
    { "user_id": 100, "date": "2019-10-18", "page_views": 872, "clicks": 930 },
    { "user_id": 101, "date": "2019-10-18", "page_views": 135, "clicks": 143 },
    { "user_id": 103, "date": "2019-10-18", "page_views": 340, "clicks": 299 },
    { "user_id": 104, "date": "2019-10-18", "page_views": 204, "clicks": 387 },
    { "user_id": 106, "date": "2019-10-18", "page_views": 232, "clicks": 515 },
    { "user_id": 107, "date": "2019-10-18", "page_views": 928, "clicks": 382 },
    { "user_id": 109, "date": "2019-10-18", "page_views": 629, "clicks": 573 },
    { "user_id": 110, "date": "2019-10-18", "page_views": 900, "clicks": 107 },
    { "user_id": 111, "date": "2019-10-18", "page_views": 756, "clicks": 629 },
    { "user_id": 112, "date": "2019-10-18", "page_views": 576, "clicks": 932 },
    { "user_id": 113, "date": "2019-10-18", "page_views": 389, "clicks": 497 },
    { "user_id": 114, "date": "2019-10-18", "page_views": 647, "clicks": 767 },
    { "user_id": 115, "date": "2019-10-18", "page_views": 140, "clicks": 286 },
    { "user_id": 116, "date": "2019-10-18", "page_views": 983, "clicks": 847 },
    { "user_id": 117, "date": "2019-10-18", "page_views": 798, "clicks": 601 },
    { "user_id": 119, "date": "2019-10-18", "page_views": 912, "clicks": 266 },
    { "user_id": 121, "date": "2019-10-18", "page_views": 741, "clicks": 607 },
    { "user_id": 122, "date": "2019-10-18", "page_views": 818, "clicks": 751 },
    { "user_id": 123, "date": "2019-10-18", "page_views": 574, "clicks": 476 },
    { "user_id": 124, "date": "2019-10-18", "page_views": 875, "clicks": 852 },
    { "user_id": 125, "date": "2019-10-18", "page_views": 804, "clicks": 757 },
    { "user_id": 126, "date": "2019-10-18", "page_views": 188, "clicks": 476 },
    { "user_id": 127, "date": "2019-10-18", "page_views": 605, "clicks": 692 },
    { "user_id": 128, "date": "2019-10-18", "page_views": 991, "clicks": 397 },
    { "user_id": 130, "date": "2019-10-18", "page_views": 658, "clicks": 272 },
    { "user_id": 132, "date": "2019-10-18", "page_views": 851, "clicks": 947 },
    { "user_id": 133, "date": "2019-10-18", "page_views": 297, "clicks": 184 },
    { "user_id": 134, "date": "2019-10-18", "page_views": 390, "clicks": 912 },
    { "user_id": 135, "date": "2019-10-18", "page_views": 889, "clicks": 551 },
    { "user_id": 136, "date": "2019-10-18", "page_views": 433, "clicks": 233 },
    { "user_id": 138, "date": "2019-10-18", "page_views": 403, "clicks": 448 },
    { "user_id": 139, "date": "2019-10-18", "page_views": 390, "clicks": 517 },
    { "user_id": 141, "date": "2019-10-18", "page_views": 242, "clicks": 366 },
    { "user_id": 142, "date": "2019-10-18", "page_views": 615, "clicks": 179 },
    { "user_id": 143, "date": "2019-10-18", "page_views": 982, "clicks": 728 },
    { "user_id": 144, "date": "2019-10-18", "page_views": 527, "clicks": 833 },
    { "user_id": 146, "date": "2019-10-18", "page_views": 775, "clicks": 624 },
    { "user_id": 147, "date": "2019-10-18", "page_views": 818, "clicks": 621 },
    { "user_id": 149, "date": "2019-10-18", "page_views": 455, "clicks": 159 },
    { "user_id": 150, "date": "2019-10-18", "page_views": 794, "clicks": 496 },
    { "user_id": 1, "date": "2019-10-19", "page_views": 912, "clicks": 294 },
    { "user_id": 2, "date": "2019-10-19", "page_views": 881, "clicks": 697 },
    { "user_id": 3, "date": "2019-10-19", "page_views": 976, "clicks": 424 },
    { "user_id": 4, "date": "2019-10-19", "page_views": 459, "clicks": 919 },
    { "user_id": 5, "date": "2019-10-19", "page_views": 692, "clicks": 356 },
    { "user_id": 6, "date": "2019-10-19", "page_views": 509, "clicks": 240 },
    { "user_id": 7, "date": "2019-10-19", "page_views": 847, "clicks": 486 },
    { "user_id": 8, "date": "2019-10-19", "page_views": 257, "clicks": 157 },
    { "user_id": 9, "date": "2019-10-19", "page_views": 445, "clicks": 512 },
    { "user_id": 10, "date": "2019-10-19", "page_views": 666, "clicks": 438 },
    { "user_id": 11, "date": "2019-10-19", "page_views": 816, "clicks": 188 },
    { "user_id": 12, "date": "2019-10-19", "page_views": 148, "clicks": 308 },
    { "user_id": 13, "date": "2019-10-19", "page_views": 347, "clicks": 305 },
    { "user_id": 14, "date": "2019-10-19", "page_views": 548, "clicks": 470 },
    { "user_id": 15, "date": "2019-10-19", "page_views": 122, "clicks": 596 },
    { "user_id": 17, "date": "2019-10-19", "page_views": 262, "clicks": 704 },
    { "user_id": 18, "date": "2019-10-19", "page_views": 495, "clicks": 784 },
    { "user_id": 21, "date": "2019-10-19", "page_views": 931, "clicks": 899 },
    { "user_id": 22, "date": "2019-10-19", "page_views": 953, "clicks": 182 },
    { "user_id": 23, "date": "2019-10-19", "page_views": 279, "clicks": 216 },
    { "user_id": 25, "date": "2019-10-19", "page_views": 543, "clicks": 934 },
    { "user_id": 26, "date": "2019-10-19", "page_views": 377, "clicks": 106 },
    { "user_id": 27, "date": "2019-10-19", "page_views": 722, "clicks": 871 },
    { "user_id": 29, "date": "2019-10-19", "page_views": 553, "clicks": 164 },
    { "user_id": 30, "date": "2019-10-19", "page_views": 309, "clicks": 138 },
    { "user_id": 32, "date": "2019-10-19", "page_views": 651, "clicks": 371 },
    { "user_id": 33, "date": "2019-10-19", "page_views": 267, "clicks": 557 },
    { "user_id": 34, "date": "2019-10-19", "page_views": 589, "clicks": 864 },
    { "user_id": 35, "date": "2019-10-19", "page_views": 794, "clicks": 856 },
    { "user_id": 37, "date": "2019-10-19", "page_views": 380, "clicks": 887 },
    { "user_id": 38, "date": "2019-10-19", "page_views": 479, "clicks": 173 },
    { "user_id": 39, "date": "2019-10-19", "page_views": 538, "clicks": 596 },
    { "user_id": 40, "date": "2019-10-19", "page_views": 701, "clicks": 791 },
    { "user_id": 41, "date": "2019-10-19", "page_views": 284, "clicks": 838 },
    { "user_id": 42, "date": "2019-10-19", "page_views": 366, "clicks": 361 },
    { "user_id": 43, "date": "2019-10-19", "page_views": 829, "clicks": 569 },
    { "user_id": 44, "date": "2019-10-19", "page_views": 834, "clicks": 341 },
    { "user_id": 45, "date": "2019-10-19", "page_views": 418, "clicks": 794 },
    { "user_id": 46, "date": "2019-10-19", "page_views": 816, "clicks": 681 },
    { "user_id": 47, "date": "2019-10-19", "page_views": 538, "clicks": 173 },
    { "user_id": 48, "date": "2019-10-19", "page_views": 303, "clicks": 582 },
    { "user_id": 49, "date": "2019-10-19", "page_views": 396, "clicks": 163 },
    { "user_id": 50, "date": "2019-10-19", "page_views": 799, "clicks": 173 },
    { "user_id": 51, "date": "2019-10-19", "page_views": 153, "clicks": 787 },
    { "user_id": 52, "date": "2019-10-19", "page_views": 457, "clicks": 315 },
    { "user_id": 53, "date": "2019-10-19", "page_views": 975, "clicks": 603 },
    { "user_id": 54, "date": "2019-10-19", "page_views": 317, "clicks": 306 },
    { "user_id": 55, "date": "2019-10-19", "page_views": 825, "clicks": 170 },
    { "user_id": 56, "date": "2019-10-19", "page_views": 300, "clicks": 469 },
    { "user_id": 57, "date": "2019-10-19", "page_views": 115, "clicks": 141 },
    { "user_id": 58, "date": "2019-10-19", "page_views": 471, "clicks": 693 },
    { "user_id": 59, "date": "2019-10-19", "page_views": 815, "clicks": 102 },
    { "user_id": 60, "date": "2019-10-19", "page_views": 924, "clicks": 147 },
    { "user_id": 61, "date": "2019-10-19", "page_views": 150, "clicks": 687 },
    { "user_id": 62, "date": "2019-10-19", "page_views": 208, "clicks": 984 },
    { "user_id": 63, "date": "2019-10-19", "page_views": 521, "clicks": 271 },
    { "user_id": 64, "date": "2019-10-19", "page_views": 323, "clicks": 832 },
    { "user_id": 65, "date": "2019-10-19", "page_views": 956, "clicks": 477 },
    { "user_id": 66, "date": "2019-10-19", "page_views": 915, "clicks": 770 },
    { "user_id": 67, "date": "2019-10-19", "page_views": 314, "clicks": 281 },
    { "user_id": 68, "date": "2019-10-19", "page_views": 609, "clicks": 697 },
    { "user_id": 69, "date": "2019-10-19", "page_views": 898, "clicks": 516 },
    { "user_id": 71, "date": "2019-10-19", "page_views": 199, "clicks": 855 },
    { "user_id": 72, "date": "2019-10-19", "page_views": 269, "clicks": 644 },
    { "user_id": 73, "date": "2019-10-19", "page_views": 148, "clicks": 760 },
    { "user_id": 74, "date": "2019-10-19", "page_views": 176, "clicks": 187 },
    { "user_id": 75, "date": "2019-10-19", "page_views": 316, "clicks": 123 },
    { "user_id": 76, "date": "2019-10-19", "page_views": 943, "clicks": 208 },
    { "user_id": 77, "date": "2019-10-19", "page_views": 849, "clicks": 458 },
    { "user_id": 78, "date": "2019-10-19", "page_views": 132, "clicks": 220 },
    { "user_id": 79, "date": "2019-10-19", "page_views": 165, "clicks": 938 },
    { "user_id": 80, "date": "2019-10-19", "page_views": 143, "clicks": 951 },
    { "user_id": 81, "date": "2019-10-19", "page_views": 708, "clicks": 778 },
    { "user_id": 82, "date": "2019-10-19", "page_views": 684, "clicks": 260 },
    { "user_id": 84, "date": "2019-10-19", "page_views": 623, "clicks": 573 },
    { "user_id": 85, "date": "2019-10-19", "page_views": 933, "clicks": 416 },
    { "user_id": 86, "date": "2019-10-19", "page_views": 577, "clicks": 643 },
    { "user_id": 87, "date": "2019-10-19", "page_views": 429, "clicks": 440 },
    { "user_id": 88, "date": "2019-10-19", "page_views": 521, "clicks": 516 },
    { "user_id": 89, "date": "2019-10-19", "page_views": 912, "clicks": 450 },
    { "user_id": 90, "date": "2019-10-19", "page_views": 973, "clicks": 502 },
    { "user_id": 92, "date": "2019-10-19", "page_views": 720, "clicks": 298 },
    { "user_id": 93, "date": "2019-10-19", "page_views": 872, "clicks": 864 },
    { "user_id": 94, "date": "2019-10-19", "page_views": 785, "clicks": 218 },
    { "user_id": 95, "date": "2019-10-19", "page_views": 548, "clicks": 522 },
    { "user_id": 96, "date": "2019-10-19", "page_views": 819, "clicks": 636 },
    { "user_id": 99, "date": "2019-10-19", "page_views": 370, "clicks": 643 },
    { "user_id": 100, "date": "2019-10-19", "page_views": 297, "clicks": 408 },
    { "user_id": 101, "date": "2019-10-19", "page_views": 112, "clicks": 812 },
    { "user_id": 103, "date": "2019-10-19", "page_views": 235, "clicks": 701 },
    { "user_id": 104, "date": "2019-10-19", "page_views": 389, "clicks": 714 },
    { "user_id": 105, "date": "2019-10-19", "page_views": 590, "clicks": 214 },
    { "user_id": 106, "date": "2019-10-19", "page_views": 382, "clicks": 468 },
    { "user_id": 107, "date": "2019-10-19", "page_views": 342, "clicks": 858 },
    { "user_id": 109, "date": "2019-10-19", "page_views": 384, "clicks": 530 },
    { "user_id": 110, "date": "2019-10-19", "page_views": 182, "clicks": 821 },
    { "user_id": 111, "date": "2019-10-19", "page_views": 236, "clicks": 312 },
    { "user_id": 112, "date": "2019-10-19", "page_views": 514, "clicks": 849 },
    { "user_id": 113, "date": "2019-10-19", "page_views": 549, "clicks": 826 },
    { "user_id": 114, "date": "2019-10-19", "page_views": 854, "clicks": 741 },
    { "user_id": 115, "date": "2019-10-19", "page_views": 669, "clicks": 558 },
    { "user_id": 116, "date": "2019-10-19", "page_views": 889, "clicks": 232 },
    { "user_id": 117, "date": "2019-10-19", "page_views": 766, "clicks": 180 },
    { "user_id": 119, "date": "2019-10-19", "page_views": 423, "clicks": 265 },
    { "user_id": 121, "date": "2019-10-19", "page_views": 986, "clicks": 233 },
    { "user_id": 122, "date": "2019-10-19", "page_views": 976, "clicks": 251 },
    { "user_id": 123, "date": "2019-10-19", "page_views": 793, "clicks": 622 },
    { "user_id": 124, "date": "2019-10-19", "page_views": 836, "clicks": 872 },
    { "user_id": 125, "date": "2019-10-19", "page_views": 315, "clicks": 579 },
    { "user_id": 126, "date": "2019-10-19", "page_views": 157, "clicks": 293 },
    { "user_id": 127, "date": "2019-10-19", "page_views": 672, "clicks": 877 },
    { "user_id": 128, "date": "2019-10-19", "page_views": 296, "clicks": 427 },
    { "user_id": 129, "date": "2019-10-19", "page_views": 935, "clicks": 184 },
    { "user_id": 130, "date": "2019-10-19", "page_views": 194, "clicks": 755 },
    { "user_id": 132, "date": "2019-10-19", "page_views": 812, "clicks": 826 },
    { "user_id": 133, "date": "2019-10-19", "page_views": 196, "clicks": 358 },
    { "user_id": 134, "date": "2019-10-19", "page_views": 938, "clicks": 316 },
    { "user_id": 135, "date": "2019-10-19", "page_views": 314, "clicks": 680 },
    { "user_id": 136, "date": "2019-10-19", "page_views": 120, "clicks": 834 },
    { "user_id": 138, "date": "2019-10-19", "page_views": 519, "clicks": 488 },
    { "user_id": 139, "date": "2019-10-19", "page_views": 159, "clicks": 615 },
    { "user_id": 141, "date": "2019-10-19", "page_views": 306, "clicks": 303 },
    { "user_id": 142, "date": "2019-10-19", "page_views": 376, "clicks": 884 },
    { "user_id": 143, "date": "2019-10-19", "page_views": 236, "clicks": 788 },
    { "user_id": 144, "date": "2019-10-19", "page_views": 647, "clicks": 747 },
    { "user_id": 146, "date": "2019-10-19", "page_views": 363, "clicks": 566 },
    { "user_id": 147, "date": "2019-10-19", "page_views": 981, "clicks": 234 },
    { "user_id": 149, "date": "2019-10-19", "page_views": 949, "clicks": 894 },
    { "user_id": 150, "date": "2019-10-19", "page_views": 216, "clicks": 858 }
  ]
}
